queuelib/__init__.py
queuelib/pqueue.py
queuelib/queue.py
queuelib/tests/__init__.py
queuelib/tests/test_pqueue.py
queuelib/tests/test_queue.py
queuelib-1.4.1.dist-info/top_level.txt
queuelib-1.4.1.dist-info/METADATA
queuelib-1.4.1.dist-info/DESCRIPTION.rst
queuelib-1.4.1.dist-info/metadata.json
queuelib-1.4.1.dist-info/WHEEL
queuelib-1.4.1.dist-info/RECORD
